pyeff/__init__.py
pyeff/fs.py
pyeff/git.py
pyeff/hash.py
pyeff/indent.py
pyeff/json.py
pyeff/lines.py
pyeff/logger.py
pyeff/shell.py
pyeff/yaml.py
tests/test.py
pyeff-0.1.3.dist-info/LICENSE
pyeff-0.1.3.dist-info/METADATA
pyeff-0.1.3.dist-info/WHEEL
pyeff-0.1.3.dist-info/top_level.txt
pyeff-0.1.3.dist-info/RECORD
