Metadata-Version: 2.1
Name: pyeff
Version: 0.1.3
Summary: Small Python lib, User friendly API for daily python code.
Home-page: https://github.com/fanfeilong/pyeff.git
Author: Fan Fei Long
Author-email: fanfeilong@gmail.com
License: MIT
Classifier: Topic :: Utilities
Classifier: Programming Language :: Python :: 3.5
Classifier: Programming Language :: Python :: 3.6
Classifier: Programming Language :: Python :: 3.7
Classifier: Programming Language :: Python :: 3.8
Classifier: Programming Language :: Python :: 3.9
Classifier: Programming Language :: Python :: 3.10
Classifier: Programming Language :: Python :: 3 :: Only
Classifier: License :: OSI Approved :: MIT License
License-File: LICENSE
Requires-Dist: loguru
Requires-Dist: requests
Requires-Dist: pyyaml >=5.1
Requires-Dist: pyyaml-include >=2.0
Requires-Dist: aiofiles
